pygsdata
